[
  {
    "name": "Ac Milan",
    "logo": "ac-milan.png",
    "country": "italy",
    "league": "serie a"
  },
  {
    "name": "Atalanta",
    "logo": "atalanta.png",
    "country": "italy",
    "league": "serie a"
  },
  {
    "name": "Bologna",
    "logo": "bologna.png",
    "country": "italy",
    "league": "serie a"
  },
  {
    "name": "Cagliari",
    "logo": "cagliari.png",
    "country": "italy",
    "league": "serie a"
  },
  {
    "name": "Empoli",
    "logo": "empoli.png",
    "country": "italy",
    "league": "serie a"
  },
  {
    "name": "Fiorentina",
    "logo": "fiorentina.png",
    "country": "italy",
    "league": "serie a"
  },
  {
    "name": "Frosinone",
    "logo": "frosinone.png",
    "country": "italy",
    "league": "serie a"
  },
  {
    "name": "Genoa",
    "logo": "genoa.png",
    "country": "italy",
    "league": "serie a"
  },  
  {
    "name": "Inter",
    "logo": "inter.png",
    "country": "italy",
    "league": "serie a"
  },
  {
    "name": "Juventus",
    "logo": "juventus.png",
    "country": "italy",
    "league": "serie a"
  },
  {
    "name": "Lazio",
    "logo": "lazio.png",
    "country": "italy",
    "league": "serie a"
  },
  {
    "name": "Lecce",
    "logo": "lecce.png",
    "country": "italy",
    "league": "serie a"
  },
  {
    "name": "Monza",
    "logo": "monza.png",
    "country": "italy",
    "league": "serie a"
  },
  {
    "name": "Napoli",
    "logo": "napoli.png",
    "country": "italy",
    "league": "serie a"
  },
  {
    "name": "Roma",
    "logo": "roma.png",
    "country": "italy",
    "league": "serie a"
  },
  {
    "name": "Salernitana",
    "logo": "salernitana.png",
    "country": "italy",
    "league": "serie a"
  },
  {
    "name": "Sassuolo",
    "logo": "sassuolo.png",
    "country": "italy",
    "league": "serie a"
  },
  {
    "name": "Torino",
    "logo": "torino.png",
    "country": "italy",
    "league": "serie a"
  },
  {
    "name": "Udinese",
    "logo": "udinese.png",
    "country": "italy",
    "league": "serie a"
  },
  {
    "name": "Verona",
    "logo": "verona.png",
    "country": "italy",
    "league": "serie a"
  }
]